genderclf/__init__.py
genderclf/genderclf.py
genderclf/models/gender_logit_model.pkl
genderclf/models/gender_nv_model.pkl
genderclf/models/gender_vectorizer.pkl
genderclf-0.0.1.dist-info/WHEEL
genderclf-0.0.1.dist-info/METADATA
genderclf-0.0.1.dist-info/RECORD
